LICENSE.txt
MANIFEST.in
Makefile
README.txt
setup.py
facct/GLedger.py
facct/IncomeStatement.py
facct/__init__.py
facct/bench.py
facct/config.py
facct/generate_all.py
facct/i18n.py
facct/init_year.py
facct/journal.py
facct/override_tmpl_jnl.py
facct/path_mngt.py
facct.egg-info/PKG-INFO
facct.egg-info/SOURCES.txt
facct.egg-info/dependency_links.txt
facct.egg-info/requires.txt
facct.egg-info/top_level.txt
facct.egg-info/zip-safe
facct/bench_infra/__init__.py
facct/bench_infra/benchs/accounts/2010/2010.csv
facct/bench_infra/benchs/accounts/2010/2010.gl.csv
facct/bench_infra/benchs/accounts/2010/IncomeStatement_2010.csv
facct/bench_infra/benchs/accounts/2010/balance_sheet_2010.csv
facct/bench_infra/benchs/accounts/2010/journal.ori.csv
facct/bench_infra/benchs/accounts/2010/journal_tmpl.csv
facct/bench_infra/benchs/accounts/2010/tribunal_commerce/ANNEXE_2010_My_Cute_Company.pdf
facct/bench_infra/benchs/accounts/2010/tribunal_commerce/BILAN_2010_My_Cute_Company.pdf
facct/bench_infra/benchs/accounts/2010/tribunal_commerce/COMPTE_DE_RESULTAT_2010_My_Cute_Company.pdf
facct/bench_infra/benchs/accounts/2011/2011.csv
facct/bench_infra/benchs/accounts/2011/2011.gl.csv
facct/bench_infra/benchs/accounts/2011/IncomeStatement_2011.csv
facct/bench_infra/benchs/accounts/2011/balance_sheet_2011.csv
facct/bench_infra/benchs/accounts/2011/journal.ori.csv
facct/bench_infra/benchs/accounts/2011/journal_tmpl.csv
facct/bench_infra/benchs/accounts/2011/hsbc/releve-hsbc.csv
facct/bench_infra/benchs/accounts/2011/tribunal_commerce/ANNEXE_2011_My_Cute_Company.pdf
facct/bench_infra/benchs/accounts/2011/tribunal_commerce/BILAN_2011_My_Cute_Company.pdf
facct/bench_infra/benchs/accounts/2011/tribunal_commerce/COMPTE_DE_RESULTAT_2011_My_Cute_Company.pdf
facct/bench_infra/benchs/accounts/2012/2012.csv
facct/bench_infra/benchs/accounts/2012/2012.gl.csv
facct/bench_infra/benchs/accounts/2012/IncomeStatement_2012.csv
facct/bench_infra/benchs/accounts/2012/balance_sheet_2012.csv
facct/bench_infra/benchs/accounts/2012/journal.ori.csv
facct/bench_infra/benchs/accounts/2012/journal_tmpl.csv
