Metadata-Version: 1.1
Name: facct
Version: 0.1.6
Summary: Fig's accountancy tool
Home-page: http://eric.figuereo.free.fr
Author: Eric F.
Author-email: efigue.foss@free.fr
License: GPLV3+
Platform: UNKNOWN
Classifier: Development Status :: 3 - Alpha
Classifier: Environment :: Console
Classifier: Intended Audience :: Financial and Insurance Industry
Classifier: License :: OSI Approved :: GNU General Public License v3 or later (GPLv3+)
Classifier: Operating System :: OS Independent
Classifier: Programming Language :: Python
Classifier: Programming Language :: Python :: 2
Classifier: Programming Language :: Python :: 3
Classifier: Natural Language :: English
Classifier: Natural Language :: French
Classifier: Topic :: Office/Business
Classifier: Topic :: Office/Business :: Financial :: Accounting
